{"url":"https://api.github.com/repos/kirajcg/pyscbwrapper/languages","status":200,"headers":{"access-control-allow-origin":"*","access-control-expose-headers":"ETag, Link, Location, Retry-After, X-GitHub-OTP, X-RateLimit-Limit, X-RateLimit-Remaining, X-RateLimit-Used, X-RateLimit-Resource, X-RateLimit-Reset, X-OAuth-Scopes, X-Accepted-OAuth-Scopes, X-Poll-Interval, X-GitHub-Media-Type, X-GitHub-SSO, X-GitHub-Request-Id, Deprecation, Sunset","cache-control":"private, max-age=60, s-maxage=60","content-encoding":"gzip","content-security-policy":"default-src 'none'","content-type":"application/json; charset=utf-8","date":"Fri, 04 Apr 2025 10:49:55 GMT","etag":"W/\"5d9cc4b5cb7e43971ec76a3d0c1242e9e08dd9129444472f0dac8baf42e4ddd3\"","github-authentication-token-expiration":"2025-08-21 22:00:00 UTC","last-modified":"Fri, 04 Apr 2025 08:20:32 GMT","referrer-policy":"origin-when-cross-origin, strict-origin-when-cross-origin","server":"github.com","strict-transport-security":"max-age=31536000; includeSubdomains; preload","transfer-encoding":"chunked","vary":"Accept, Authorization, Cookie, X-GitHub-OTP,Accept-Encoding, Accept, X-Requested-With","x-accepted-oauth-scopes":"","x-content-type-options":"nosniff","x-frame-options":"deny","x-github-api-version-selected":"2022-11-28","x-github-media-type":"github.v3; format=json","x-github-request-id":"7BC5:27BC68:1D01C1F:39E7D6E:67EFB953","x-oauth-scopes":"admin:org, audit_log, read:discussion, read:enterprise, read:gpg_key, read:project, read:ssh_signing_key, repo","x-ratelimit-limit":"5000","x-ratelimit-remaining":"4944","x-ratelimit-reset":"1743767071","x-ratelimit-resource":"core","x-ratelimit-used":"56","x-xss-protection":"0"},"data":{"Jupyter Notebook":2074039,"Python":4106}}