{"url":"https://api.github.com/repos/EnterpriseCharacteristicsESSnetBigData/StarterKit/languages","status":200,"headers":{"access-control-allow-origin":"*","access-control-expose-headers":"ETag, Link, Location, Retry-After, X-GitHub-OTP, X-RateLimit-Limit, X-RateLimit-Remaining, X-RateLimit-Used, X-RateLimit-Resource, X-RateLimit-Reset, X-OAuth-Scopes, X-Accepted-OAuth-Scopes, X-Poll-Interval, X-GitHub-Media-Type, X-GitHub-SSO, X-GitHub-Request-Id, Deprecation, Sunset","cache-control":"private, max-age=60, s-maxage=60","content-encoding":"gzip","content-security-policy":"default-src 'none'","content-type":"application/json; charset=utf-8","date":"Thu, 05 Jun 2025 13:00:13 GMT","etag":"W/\"a6c315e199d53c190fd34d2e7d3a19d52a2401a497653159c654d088cab987b5\"","github-authentication-token-expiration":"2025-08-21 22:00:00 UTC","last-modified":"Sat, 18 Jan 2025 23:07:01 GMT","referrer-policy":"origin-when-cross-origin, strict-origin-when-cross-origin","server":"github.com","strict-transport-security":"max-age=31536000; includeSubdomains; preload","transfer-encoding":"chunked","vary":"Accept, Authorization, Cookie, X-GitHub-OTP,Accept-Encoding, Accept, X-Requested-With","x-accepted-oauth-scopes":"","x-content-type-options":"nosniff","x-frame-options":"deny","x-github-api-version-selected":"2022-11-28","x-github-media-type":"github.v3; format=json","x-github-request-id":"4BCC:1C017A:1897E57:316F9C4:684194DD","x-oauth-scopes":"admin:org, audit_log, read:discussion, read:enterprise, read:gpg_key, read:project, read:ssh_signing_key, repo","x-ratelimit-limit":"5000","x-ratelimit-remaining":"4874","x-ratelimit-reset":"1749130466","x-ratelimit-resource":"core","x-ratelimit-used":"126","x-xss-protection":"0"},"data":{"Jupyter Notebook":654776,"Python":88339}}