{"Package":"StatMatch","Version":"1.4.3","Date":"2025-01-08","Title":"Statistical Matching or Data Fusion","Authors@R":"person(given = \"Marcello\",\nfamily = \"D'Orazio\",\nrole = c(\"aut\", \"cre\"),\nemail = \"mdo.statmatch@gmail.com\")","Author":"Marcello D'Orazio [aut, cre]","Maintainer":"Marcello D'Orazio <mdo.statmatch@gmail.com>","Depends":{"R":">= 2.7.0","proxy":"*","survey":"*","lpSolve":"*","ggplot2":"*","dplyr":"*"},"Suggests":{"Hmisc":"*","MASS":"*","mipfp":"*","clue":"*","RANN":"*","randomForest":"*","nnet":"*","glmnet":"*","naivebayes":"*"},"Description":"Integration of two data sources referred to the same target population which share a number of variables. Some functions can also be used to impute missing values in data sets through hot deck imputation methods. Methods to perform statistical matching when dealing  with data from complex sample surveys are available too.","License":"GPL (>= 2)","URL":"https://github.com/marcellodo/StatMatch,\nhttps://github.com/marcellodo/StatMatch/tree/master/Tutorials_Vignette_OtherDocs","NeedsCompilation":"no","Packaged":"2025-01-08 21:30:09 UTC; marc&gio","Repository":"CRAN","Date/Publication":"2025-01-08 22:00:02 UTC","crandb_file_date":"2025-01-08 22:46:27","MD5sum":"852a8a37b2fcabacae78063be5f45622","date":"2025-01-08T21:00:02+00:00","releases":[]}